nornir_apps/__init__.py
nornir_apps/cli.py
nornir_apps/commands.local.py
nornir_apps/console.py
nornir_apps/hookspecs.py
nornir_apps/plugins.py
nornir_apps/version.py
nornir_apps/commands/__init__.py
nornir_apps/commands/common.py
nornir_apps/commands/napalm_configure_cmd.py
nornir_apps/commands/napalm_get_cmd.py
nornir_apps/commands/napalm_ping_cmd.py
nornir_apps/commands/napalm_validate_cmd.py
nornir_apps-0.0.3.dist-info/METADATA
nornir_apps-0.0.3.dist-info/WHEEL
nornir_apps-0.0.3.dist-info/entry_points.txt
nornir_apps-0.0.3.dist-info/top_level.txt
nornir_apps-0.0.3.dist-info/RECORD
