Metadata-Version: 2.1
Name: nornir-apps
Version: 0.0.3
Summary: Lightweight pluggable CLI for nornir scripts
Home-page: https://github.com/ttafsir/nornir-apps
Author: Tafsir Thiam
Author-email: ttafsir@gmail.com
License: MIT license
Keywords: nornir,nornir-cli
Classifier: Development Status :: 3 - Alpha
Classifier: Intended Audience :: Developers
Classifier: License :: OSI Approved :: MIT License
Classifier: Natural Language :: English
Classifier: Programming Language :: Python :: 3
Classifier: Programming Language :: Python :: 3.7
Classifier: Programming Language :: Python :: 3.8
Classifier: Programming Language :: Python :: 3.9
Requires-Python: >=3.7
Requires-Dist: click (==8.1.3)
Requires-Dist: nornir (==3.3.0)
Requires-Dist: nornir-napalm (==0.2.0)
Requires-Dist: nornir-utils (==0.2.0)
Requires-Dist: rich (==10.16.2)
Requires-Dist: pluggy (<1.1,>=1.0)
Provides-Extra: test
Requires-Dist: pytest ; extra == 'test'
Requires-Dist: pytest-cov ; extra == 'test'
